clease_cxx.cpython-314-x86_64-linux-musl.so
clease/__init__.py
clease/_version.txt
clease/basis_function.py
clease/cluster_coverage.py
clease/convexhull.py
clease/corr_func.py
clease/data_manager.py
clease/data_normalizer.py
clease/db_util.py
clease/evaluate.py
clease/geometry.py
clease/gramSchmidthMonomials.py
clease/interactive_plot.py
clease/jsonio.py
clease/logging_utils.py
clease/mc_trajectory_extractor.py
clease/mp_logger.py
clease/plot_post_process.py
clease/sparsifier.py
clease/structure_mapper.py
clease/svd.py
clease/tools.py
clease/version.py
clease/calculator/__init__.py
clease/calculator/calc_cache.py
clease/calculator/clease.py
clease/calculator/clease_vol_dep.py
clease/calculator/util.py
clease/cli/__init__.py
clease/cli/cluster.py
clease/cli/db.py
clease/cli/main.py
clease/cli/reconfigure.py
clease/cluster/__init__.py
clease/cluster/cluster.py
clease/cluster/cluster_fingerprint.py
clease/cluster/cluster_generator.py
clease/cluster/cluster_info_mapper.py
clease/cluster/cluster_list.py
clease/cluster/cluster_manager.py
clease/cluster/utils.py
clease/datastructures/__init__.py
clease/datastructures/figure.py
clease/datastructures/four_vector.py
clease/datastructures/mc_step.py
clease/datastructures/system_changes.py
clease/datastructures/trans_matrix.py
clease/montecarlo/__init__.py
clease/montecarlo/averager.py
clease/montecarlo/barrier_models.py
clease/montecarlo/base.py
clease/montecarlo/bias_potential.py
clease/montecarlo/binned_bias_potential.py
clease/montecarlo/exponential_filter.py
clease/montecarlo/gaussian_kernel_bias_potential.py
clease/montecarlo/kinetic_monte_carlo.py
clease/montecarlo/kmc_events.py
clease/montecarlo/mc_evaluator.py
clease/montecarlo/metadynamics_sampler.py
clease/montecarlo/montecarlo.py
clease/montecarlo/random_bias_with_memory.py
clease/montecarlo/sgc_montecarlo.py
clease/montecarlo/swap_move_index_tracker.py
clease/montecarlo/trial_move_generator.py
clease-1.2.0.dist-info/METADATA
clease-1.2.0.dist-info/WHEEL
clease-1.2.0.dist-info/entry_points.txt
clease-1.2.0.dist-info/top_level.txt
clease-1.2.0.dist-info/RECORD
clease-1.2.0.dist-info/licenses/LICENSE.md
clease-1.2.0.dist-info/sboms/auditwheel.cdx.json
