Metadata-Version: 2.4
Name: clease
Version: 1.2.0
Summary: CLuster Expansion in Atomistic Simulation Environment
Home-page: https://gitlab.com/computationalmaterials/clease/
Author: J. H. Chang, D. Kleiven, A. S. Tygesen
Author-email: jchang@dtu.dk, david.kleiven@ntnu.no, alexty@dtu.dk
License: MPL-2.0
Project-URL: Documentation, https://clease.readthedocs.io/
Project-URL: Source, https://gitlab.com/computationalmaterials/clease/
Keywords: Cluster Expansion,Monte Carlo,Computational materials,Materials research
Classifier: Development Status :: 5 - Production/Stable
Classifier: License :: OSI Approved :: Mozilla Public License 2.0 (MPL 2.0)
Classifier: Programming Language :: Python :: 3
Classifier: Topic :: Scientific/Engineering :: Physics
Classifier: Topic :: Scientific/Engineering :: Chemistry
Requires-Python: >=3.10
License-File: LICENSE.md
Requires-Dist: ase>=3.22
Requires-Dist: numpy
Requires-Dist: cython
Requires-Dist: matplotlib
Requires-Dist: spglib
Requires-Dist: scikit-learn
Requires-Dist: typing_extensions
Requires-Dist: Deprecated
Requires-Dist: click>=8.0.0
Requires-Dist: attrs>=21.4.0
Requires-Dist: scipy>=1.7.0
Requires-Dist: packaging
Requires-Dist: threadpoolctl
Provides-Extra: doc
Requires-Dist: sphinx; extra == "doc"
Requires-Dist: sphinx_rtd_theme; extra == "doc"
Provides-Extra: test
Requires-Dist: pytest; extra == "test"
Requires-Dist: pytest-mock; extra == "test"
Requires-Dist: mock; extra == "test"
Requires-Dist: pytest-benchmark[histogram]>=3.4.1; extra == "test"
Requires-Dist: tox>=4; extra == "test"
Provides-Extra: dev
Requires-Dist: pip; extra == "dev"
Requires-Dist: cython; extra == "dev"
Requires-Dist: pre-commit; extra == "dev"
Requires-Dist: ipython; extra == "dev"
Requires-Dist: twine; extra == "dev"
Requires-Dist: clang-format==21.1.5; extra == "dev"
Requires-Dist: ruff==0.14.5; extra == "dev"
Requires-Dist: pyclean>=2.0.0; extra == "dev"
Requires-Dist: pytest-cov; extra == "dev"
Requires-Dist: build; extra == "dev"
Provides-Extra: gui
Requires-Dist: clease-gui; extra == "gui"
Provides-Extra: all
Requires-Dist: ipython; extra == "all"
Requires-Dist: pytest-cov; extra == "all"
Requires-Dist: tox>=4; extra == "all"
Requires-Dist: pytest-mock; extra == "all"
Requires-Dist: pip; extra == "all"
Requires-Dist: pre-commit; extra == "all"
Requires-Dist: twine; extra == "all"
Requires-Dist: cython; extra == "all"
Requires-Dist: pytest; extra == "all"
Requires-Dist: sphinx; extra == "all"
Requires-Dist: mock; extra == "all"
Requires-Dist: clang-format==21.1.5; extra == "all"
Requires-Dist: pytest-benchmark[histogram]>=3.4.1; extra == "all"
Requires-Dist: clease-gui; extra == "all"
Requires-Dist: pyclean>=2.0.0; extra == "all"
Requires-Dist: build; extra == "all"
Requires-Dist: ruff==0.14.5; extra == "all"
Requires-Dist: sphinx_rtd_theme; extra == "all"
Dynamic: license-file
Dynamic: provides-extra
